lsh_index/__init__.py
lsh_index/indexer.py
lsh_index-0.1.1.dist-info/LICENSE
lsh_index-0.1.1.dist-info/METADATA
lsh_index-0.1.1.dist-info/WHEEL
lsh_index-0.1.1.dist-info/top_level.txt
lsh_index-0.1.1.dist-info/RECORD
