Metadata-Version: 2.1
Name: lsh-index
Version: 0.1.1
Summary: Python package for implementing a Locality Sensitive Hashing (LSH) index
Home-page: https://github.com/diomandeee/lsh_index
Author: Mohamed Diomande
Author-email: gdiomande7907@gmail.com
License: MIT
Classifier: Programming Language :: Python :: 3
Classifier: License :: OSI Approved :: MIT License
Classifier: Operating System :: OS Independent
Requires-Python: >=3.6
License-File: LICENSE
Requires-Dist: numpy
Requires-Dist: scipy
